setup.py
cutandpaste.egg-info/PKG-INFO
cutandpaste.egg-info/SOURCES.txt
cutandpaste.egg-info/dependency_links.txt
cutandpaste.egg-info/top_level.txt
paste/__init__.py